j25
